armonik/__init__.py
armonik/_version.py
armonik/client/__init__.py
armonik/client/events.py
armonik/client/health_checks.py
armonik/client/partitions.py
armonik/client/results.py
armonik/client/sessions.py
armonik/client/tasks.py
armonik/client/versions.py
armonik/common/__init__.py
armonik/common/channel.py
armonik/common/enumwrapper.py
armonik/common/events.py
armonik/common/helpers.py
armonik/common/objects.py
armonik/common/filter/__init__.py
armonik/common/filter/_filter_field.py
armonik/common/filter/_message_types.py
armonik/common/filter/filter.py
armonik/protogen/__init__.py
armonik/protogen/client/__init__.py
armonik/protogen/client/applications_service_pb2.py
armonik/protogen/client/applications_service_pb2.pyi
armonik/protogen/client/applications_service_pb2_grpc.py
armonik/protogen/client/auth_service_pb2.py
armonik/protogen/client/auth_service_pb2.pyi
armonik/protogen/client/auth_service_pb2_grpc.py
armonik/protogen/client/events_service_pb2.py
armonik/protogen/client/events_service_pb2.pyi
armonik/protogen/client/events_service_pb2_grpc.py
armonik/protogen/client/health_checks_service_pb2.py
armonik/protogen/client/health_checks_service_pb2.pyi
armonik/protogen/client/health_checks_service_pb2_grpc.py
armonik/protogen/client/partitions_service_pb2.py
armonik/protogen/client/partitions_service_pb2.pyi
armonik/protogen/client/partitions_service_pb2_grpc.py
armonik/protogen/client/results_service_pb2.py
armonik/protogen/client/results_service_pb2.pyi
armonik/protogen/client/results_service_pb2_grpc.py
armonik/protogen/client/sessions_service_pb2.py
armonik/protogen/client/sessions_service_pb2.pyi
armonik/protogen/client/sessions_service_pb2_grpc.py
armonik/protogen/client/submitter_service_pb2.py
armonik/protogen/client/submitter_service_pb2.pyi
armonik/protogen/client/submitter_service_pb2_grpc.py
armonik/protogen/client/tasks_service_pb2.py
armonik/protogen/client/tasks_service_pb2.pyi
armonik/protogen/client/tasks_service_pb2_grpc.py
armonik-3.28.1.dist-info/METADATA
armonik-3.28.1.dist-info/WHEEL
armonik-3.28.1.dist-info/top_level.txt
armonik-3.28.1.dist-info/RECORD
