Metadata-Version: 2.4
Name: armonik
Version: 3.28.1
Summary: GRPC python binding for the ArmoniK orchestrator API
License: Apache v2.0 LICENSE
Project-URL: Homepage, https://github.com/aneoconsulting/ArmoniK.Api
Project-URL: Bug Tracker, https://github.com/aneoconsulting/ArmoniK/issues
Keywords: cloud,HTC,gRPC,ArmoniK,Aneo
Classifier: Programming Language :: Python :: 3
Requires-Python: >=3.7
Requires-Dist: grpcio==1.62.3
Requires-Dist: grpcio-tools==1.62.3
Requires-Dist: deprecation
Requires-Dist: cryptography>=36
Provides-Extra: tests
Requires-Dist: coverage; extra == "tests"
Requires-Dist: pytest; extra == "tests"
Requires-Dist: pytest-cov; extra == "tests"
Requires-Dist: pytest-benchmark[histogram]; extra == "tests"
Requires-Dist: requests; extra == "tests"
Provides-Extra: dev
Requires-Dist: mypy; extra == "dev"
Requires-Dist: ruff; extra == "dev"
Requires-Dist: types-protobuf; extra == "dev"
